README.rst
setup.py
asterios/__init__.py
asterios/__main__.py
asterios/__version__.py
asterios/authorization.py
asterios/config.py
asterios/level.py
asterios/routes.py
asterios/views.py
asterios.egg-info/PKG-INFO
asterios.egg-info/SOURCES.txt
asterios.egg-info/dependency_links.txt
asterios.egg-info/requires.txt
asterios.egg-info/top_level.txt
asterios/config_loader/__init__.py
asterios/config_loader/argument_parser.py
asterios/config_loader/config_modifiers.py
asterios/models/__init__.py
asterios/models/basemodel.py
asterios/models/errors.py
asterios/models/games.py
asterios/models/team_members.py
asterios/models/utils.py