Metadata-Version: 1.2
Name: asterios
Version: 2.0.1
Summary: Asterios escape game server
Home-page: https://github.com/Maillol/asterios
Author: vincent.maillol@gmail.com
Author-email: vincent.maillol@gmail.com
License: GPLv3
Keywords: Asterios escape game server
Platform: UNKNOWN
Classifier: Programming Language :: Python :: 3.5
Classifier: Programming Language :: Python :: 3.6
Classifier: Topic :: Games/Entertainment :: Puzzle Games
Classifier: License :: OSI Approved :: GNU General Public License v3 (GPLv3)
Requires-Python: >=3.5
